<graph><node><id>113</id><x>0.4</x><y>5.46</y></node><node><id>115</id><x>0.67</x><y>5.46</y></node><node><id>117</id><x>0.95</x><y>5.46</y></node><node><id>119</id><x>1.22</x><y>5.46</y></node><node><id>121</id><x>1.5</x><y>5.46</y></node><node><id>123</id><x>1.77</x><y>5.46</y></node><node><id>99</id><x>2.06</x><y>5.46</y></node><node><id>27</id><x>2.21</x><y>5.46</y></node><node><id>30</id><x>2.96</x><y>5.28</y></node><node><id>24</id><x>3.15</x><y>4.52</y></node><node><id>94</id><x>3.15</x><y>4.29</y></node><node><id>92</id><x>3.15</x><y>3.96</y></node><node><id>4</id><x>3.15</x><y>3.73</y></node><node><id>10</id><x>2.96</x><y>2.96</y></node><node><id>7</id><x>3.15</x><y>2.19</y></node><node><id>78</id><x>3.15</x><y>1.97</y></node><node><id>76</id><x>3.15</x><y>1.64</y></node><node><id>16</id><x>3.15</x><y>1.43</y></node><node><id>20</id><x>2.96</x><y>0.67</y></node><node><id>17</id><x>3.72</x><y>0.86</y></node><node><id>71</id><x>3.94</x><y>0.86</y></node><node><id>73</id><x>4.29</x><y>0.86</y></node><node><id>105</id><x>4.63</x><y>0.86</y></node><node><id>107</id><x>4.91</x><y>0.86</y></node><node><id>109</id><x>5.18</x><y>0.86</y></node><node><id>111</id><x>5.46</x><y>0.86</y></node></graph>